tkmapx/__init__.py
tkmapx/core.py
tkmapx/display.py
tkmapx-1.0.4.dist-info/licenses/LICENSE.txt
tkmapx-1.0.4.dist-info/METADATA
tkmapx-1.0.4.dist-info/WHEEL
tkmapx-1.0.4.dist-info/top_level.txt
tkmapx-1.0.4.dist-info/RECORD
