Metadata-Version: 2.4
Name: tkmapx
Version: 1.0.4
Summary: A Tkinter-based Python package for creating and visualizing simple maps with nodes and paths. (1.0.3 has other bug fixes, download this version.)
Home-page: https://github.com/Krishna-Developer5000/tkmap
Author: Nebula Company
Classifier: Development Status :: 4 - Beta
Classifier: Intended Audience :: Developers
Classifier: License :: OSI Approved :: MIT License
Classifier: Programming Language :: Python :: 3
Classifier: Programming Language :: Python :: 3.9
Classifier: Programming Language :: Python :: 3.10
Classifier: Programming Language :: Python :: 3.11
Classifier: Topic :: Software Development :: Libraries
Classifier: Topic :: Scientific/Engineering :: Visualization
Requires-Python: >=3.8
License-File: LICENSE.txt
Dynamic: home-page
Dynamic: license-file
Dynamic: requires-python
